{"day1_ts":1733029200,"members":{"2611525":{"id":2611525,"last_star_ts":0,"completion_day_level":{},"global_score":0,"stars":0,"name":"yanskee","local_score":0},"3191060":{"last_star_ts":0,"id":3191060,"completion_day_level":{},"global_score":0,"local_score":0,"name":"Marko Polak","stars":0},"427349":{"local_score":373,"name":"Blarc","stars":26,"global_score":0,"completion_day_level":{"12":{"2":{"star_index":2321637,"get_star_ts":1734019278},"1":{"get_star_ts":1733983903,"star_index":2267586}},"2":{"1":{"star_index":239187,"get_star_ts":1733118075},"2":{"star_index":259100,"get_star_ts":1733122867}},"11":{"2":{"get_star_ts":1733914180,"star_index":2165095},"1":{"get_star_ts":1733911833,"star_index":2160657}},"7":{"2":{"star_index":1493797,"get_star_ts":1733560613},"1":{"star_index":1491324,"get_star_ts":1733559517}},"6":{"1":{"star_index":1287625,"get_star_ts":1733465062},"2":{"star_index":1304884,"get_star_ts":1733471529}},"8":{"2":{"star_index":1703923,"get_star_ts":1733663536},"1":{"get_star_ts":1733654880,"star_index":1683090}},"9":{"2":{"star_index":1891305,"get_star_ts":1733762244},"1":{"get_star_ts":1733725119,"star_index":1812683}},"5":{"1":{"star_index":1070144,"get_star_ts":1733377314},"2":{"get_star_ts":1733377573,"star_index":1071562}},"10":{"1":{"get_star_ts":1733809629,"star_index":1971456},"2":{"get_star_ts":1733809658,"star_index":1971547}},"4":{"1":{"star_index":836216,"get_star_ts":1733292445},"2":{"star_index":841555,"get_star_ts":1733293761}},"3":{"2":{"get_star_ts":1733205522,"star_index":552135},"1":{"star_index":540436,"get_star_ts":1733203661}},"1":{"2":{"get_star_ts":1733035144,"star_index":23789},"1":{"get_star_ts":1733034252,"star_index":22168}},"13":{"1":{"star_index":2383939,"get_star_ts":1734070339},"2":{"star_index":2386122,"get_star_ts":1734071414}}},"last_star_ts":1734071414,"id":427349},"3782826":{"id":3782826,"last_star_ts":1734115314,"completion_day_level":{"6":{"1":{"star_index":1402672,"get_star_ts":1733510491}},"5":{"2":{"star_index":1082465,"get_star_ts":1733380262},"1":{"get_star_ts":1733378733,"star_index":1076886}},"8":{"2":{"star_index":1655278,"get_star_ts":1733642273},"1":{"star_index":1653806,"get_star_ts":1733641466}},"9":{"1":{"get_star_ts":1733724918,"star_index":1812155},"2":{"star_index":1938704,"get_star_ts":1733785197}},"11":{"1":{"star_index":2187481,"get_star_ts":1733926775},"2":{"get_star_ts":1733929838,"star_index":2193181}},"7":{"1":{"star_index":1472134,"get_star_ts":1733550960},"2":{"star_index":1477752,"get_star_ts":1733553067}},"13":{"2":{"get_star_ts":1734115314,"star_index":2455040},"1":{"star_index":2382574,"get_star_ts":1734069712}},"1":{"2":{"get_star_ts":1733094131,"star_index":193347},"1":{"star_index":190870,"get_star_ts":1733093037}},"10":{"2":{"star_index":1978320,"get_star_ts":1733812102},"1":{"star_index":1977371,"get_star_ts":1733811687}},"4":{"2":{"star_index":855551,"get_star_ts":1733297872},"1":{"star_index":849877,"get_star_ts":1733296203}},"3":{"1":{"get_star_ts":1733208173,"star_index":564220},"2":{"star_index":692728,"get_star_ts":1733240308}},"2":{"1":{"get_star_ts":1733123475,"star_index":261461},"2":{"star_index":367373,"get_star_ts":1733149302}},"12":{"1":{"get_star_ts":1734037733,"star_index":2348659}}},"global_score":0,"name":"jkuhta","stars":24,"local_score":311},"2612006":{"last_star_ts":0,"id":2612006,"completion_day_level":{},"global_score":0,"local_score":0,"name":"martinjurkovic","stars":0},"2731000":{"global_score":0,"local_score":0,"name":"Gal Petkovšek","stars":0,"last_star_ts":0,"id":2731000,"completion_day_level":{}},"657100":{"id":657100,"last_star_ts":0,"completion_day_level":{},"global_score":0,"name":"KalcMatej99","stars":0,"local_score":0},"1590937":{"completion_day_level":{"1":{"2":{"get_star_ts":1733043229,"star_index":41859},"1":{"star_index":38847,"get_star_ts":1733042152}}},"id":1590937,"last_star_ts":1733043229,"stars":2,"name":"Nik Jan Špruk","local_score":26,"global_score":0},"4357619":{"completion_day_level":{"1":{"1":{"get_star_ts":1733053594,"star_index":73798},"2":{"star_index":75684,"get_star_ts":1733054226}}},"last_star_ts":1733054226,"id":4357619,"local_score":24,"name":"Matej Miočić","stars":2,"global_score":0},"1100867":{"completion_day_level":{},"id":1100867,"last_star_ts":0,"stars":0,"name":"Iztok Bajcar","local_score":0,"global_score":0},"2570738":{"completion_day_level":{"14":{"1":{"star_index":2500500,"get_star_ts":1734156868},"2":{"get_star_ts":1734162608,"star_index":2509030}},"12":{"2":{"star_index":2269655,"get_star_ts":1733984946},"1":{"star_index":2268290,"get_star_ts":1733984251}},"2":{"1":{"get_star_ts":1733116656,"star_index":228705},"2":{"get_star_ts":1733117856,"star_index":237917}},"3":{"2":{"star_index":537525,"get_star_ts":1733203342},"1":{"get_star_ts":1733202536,"star_index":528156}},"4":{"1":{"get_star_ts":1733294346,"star_index":843622},"2":{"get_star_ts":1733295050,"star_index":846044}},"10":{"1":{"get_star_ts":1733815785,"star_index":1986352},"2":{"star_index":1987138,"get_star_ts":1733816149}},"13":{"2":{"star_index":2386031,"get_star_ts":1734071369},"1":{"star_index":2379594,"get_star_ts":1734068588}},"1":{"1":{"get_star_ts":1733029953,"star_index":8082},"2":{"get_star_ts":1733030654,"star_index":12619}},"7":{"2":{"star_index":1500883,"get_star_ts":1733563701},"1":{"get_star_ts":1733563014,"star_index":1499196}},"11":{"2":{"get_star_ts":1733897648,"star_index":2129069},"1":{"star_index":2127542,"get_star_ts":1733897035}},"9":{"2":{"star_index":1824948,"get_star_ts":1733730702},"1":{"star_index":1821559,"get_star_ts":1733729072}},"8":{"2":{"star_index":1668894,"get_star_ts":1733649171},"1":{"get_star_ts":1733646960,"star_index":1664047}},"5":{"1":{"star_index":1078297,"get_star_ts":1733379098},"2":{"star_index":1081300,"get_star_ts":1733379938}},"6":{"2":{"star_index":1313627,"get_star_ts":1733474773},"1":{"get_star_ts":1733474049,"star_index":1311723}}},"last_star_ts":1734162608,"id":2570738,"local_score":411,"name":"Bogatejc","stars":28,"global_score":0},"2419554":{"id":2419554,"last_star_ts":0,"completion_day_level":{},"global_score":0,"name":"Rok Koleša","stars":0,"local_score":0},"2524251":{"last_star_ts":1733915789,"id":2524251,"completion_day_level":{"2":{"2":{"get_star_ts":1733121152,"star_index":252655},"1":{"get_star_ts":1733120716,"star_index":250967}},"1":{"1":{"get_star_ts":1733035484,"star_index":24478},"2":{"star_index":25355,"get_star_ts":1733035953}},"10":{"2":{"star_index":2159833,"get_star_ts":1733911433},"1":{"star_index":2159291,"get_star_ts":1733911176}},"4":{"1":{"star_index":828978,"get_star_ts":1733290982},"2":{"get_star_ts":1733291343,"star_index":830951}},"3":{"1":{"star_index":526582,"get_star_ts":1733202413},"2":{"get_star_ts":1733203454,"star_index":538564}},"6":{"2":{"get_star_ts":1733469852,"star_index":1300581},"1":{"get_star_ts":1733462996,"star_index":1279092}},"8":{"1":{"star_index":1688223,"get_star_ts":1733656880},"2":{"star_index":1689901,"get_star_ts":1733657551}},"5":{"2":{"get_star_ts":1733376154,"star_index":1062666},"1":{"star_index":1059506,"get_star_ts":1733375732}},"9":{"1":{"get_star_ts":1733779659,"star_index":1928049},"2":{"star_index":1929419,"get_star_ts":1733780321}},"11":{"2":{"star_index":2167967,"get_star_ts":1733915789},"1":{"get_star_ts":1733912557,"star_index":2162037}},"7":{"1":{"star_index":1465820,"get_star_ts":1733549381},"2":{"get_star_ts":1733549615,"star_index":1466962}}},"global_score":0,"local_score":317,"name":"Nikolay Vasilev","stars":22},"2623796":{"name":"Andrej Orešnik","stars":28,"local_score":453,"global_score":0,"completion_day_level":{"6":{"1":{"star_index":1273926,"get_star_ts":1733462122},"2":{"star_index":1300862,"get_star_ts":1733469967}},"8":{"1":{"star_index":1641193,"get_star_ts":1733636527},"2":{"star_index":1647288,"get_star_ts":1733638373}},"5":{"2":{"star_index":1067360,"get_star_ts":1733376846},"1":{"get_star_ts":1733376088,"star_index":1062148}},"9":{"1":{"get_star_ts":1733721466,"star_index":1800375},"2":{"get_star_ts":1733724389,"star_index":1810755}},"11":{"1":{"get_star_ts":1733900385,"star_index":2135120},"2":{"star_index":2138670,"get_star_ts":1733902024}},"7":{"2":{"get_star_ts":1733549709,"star_index":1467415},"1":{"star_index":1462717,"get_star_ts":1733548838}},"1":{"1":{"get_star_ts":1733093039,"star_index":190874},"2":{"get_star_ts":1733093168,"star_index":191175}},"13":{"2":{"star_index":2380189,"get_star_ts":1734068805},"1":{"get_star_ts":1734067527,"star_index":2376168}},"10":{"2":{"get_star_ts":1733807800,"star_index":1961711},"1":{"get_star_ts":1733807698,"star_index":1961016}},"4":{"2":{"star_index":834834,"get_star_ts":1733292129},"1":{"get_star_ts":1733290409,"star_index":825565}},"3":{"1":{"star_index":526303,"get_star_ts":1733202390},"2":{"star_index":529740,"get_star_ts":1733202652}},"2":{"1":{"star_index":224706,"get_star_ts":1733116296},"2":{"get_star_ts":1733116609,"star_index":228209}},"12":{"1":{"star_index":2260083,"get_star_ts":1733981113},"2":{"get_star_ts":1733984567,"star_index":2268883}},"14":{"1":{"get_star_ts":1734154422,"star_index":2494271},"2":{"star_index":2503002,"get_star_ts":1734158268}}},"id":2623796,"last_star_ts":1734158268},"3392301":{"id":3392301,"last_star_ts":1734165568,"completion_day_level":{"14":{"1":{"get_star_ts":1734165568,"star_index":2513045}},"2":{"1":{"star_index":237294,"get_star_ts":1733117753},"2":{"get_star_ts":1733120133,"star_index":248728}},"12":{"1":{"get_star_ts":1733984660,"star_index":2269082},"2":{"star_index":2392765,"get_star_ts":1734075216}},"13":{"1":{"star_index":2387418,"get_star_ts":1734072091},"2":{"star_index":2389033,"get_star_ts":1734073001}},"1":{"1":{"get_star_ts":1733035088,"star_index":23667},"2":{"star_index":25601,"get_star_ts":1733036086}},"4":{"2":{"star_index":848622,"get_star_ts":1733295812},"1":{"get_star_ts":1733295242,"star_index":846734}},"3":{"2":{"star_index":534514,"get_star_ts":1733203046},"1":{"star_index":529088,"get_star_ts":1733202604}},"10":{"1":{"get_star_ts":1733809864,"star_index":1972284},"2":{"star_index":1973183,"get_star_ts":1733810112}},"9":{"1":{"star_index":1802713,"get_star_ts":1733722042},"2":{"star_index":1893448,"get_star_ts":1733763203}},"5":{"1":{"star_index":1074339,"get_star_ts":1733378129},"2":{"get_star_ts":1733379923,"star_index":1081246}},"8":{"1":{"star_index":1668823,"get_star_ts":1733649143},"2":{"get_star_ts":1733650000,"star_index":1670846}},"6":{"1":{"get_star_ts":1733462644,"star_index":1277084},"2":{"star_index":1288764,"get_star_ts":1733465410}},"7":{"1":{"get_star_ts":1733549746,"star_index":1467576},"2":{"get_star_ts":1733558352,"star_index":1488762}},"11":{"1":{"get_star_ts":1733894386,"star_index":2117830},"2":{"get_star_ts":1733896962,"star_index":2127353}}},"global_score":0,"stars":27,"name":"Peter Šarc","local_score":397},"3191257":{"last_star_ts":0,"id":3191257,"completion_day_level":{},"global_score":0,"local_score":0,"name":"Jakob Jerše","stars":0},"1578491":{"last_star_ts":0,"id":1578491,"completion_day_level":{},"global_score":0,"local_score":0,"stars":0,"name":"Aljaž Šmaljcelj"},"241985":{"completion_day_level":{"14":{"2":{"star_index":2492129,"get_star_ts":1734153828},"1":{"star_index":2489129,"get_star_ts":1734152828}},"12":{"1":{"star_index":2257446,"get_star_ts":1733980277},"2":{"get_star_ts":1733980864,"star_index":2259190}},"2":{"1":{"get_star_ts":1733115798,"star_index":219843},"2":{"star_index":221255,"get_star_ts":1733116002}},"3":{"2":{"star_index":525287,"get_star_ts":1733202304},"1":{"get_star_ts":1733202073,"star_index":523335}},"4":{"2":{"star_index":816699,"get_star_ts":1733289163},"1":{"get_star_ts":1733288588,"star_index":813560}},"10":{"2":{"get_star_ts":1733807726,"star_index":1961202},"1":{"star_index":1959657,"get_star_ts":1733807472}},"1":{"1":{"get_star_ts":1733029338,"star_index":0},"2":{"star_index":1945,"get_star_ts":1733029484}},"13":{"1":{"star_index":2372763,"get_star_ts":1734066517},"2":{"star_index":2374457,"get_star_ts":1734067060}},"7":{"1":{"get_star_ts":1733548797,"star_index":1462464},"2":{"star_index":1463925,"get_star_ts":1733549031}},"11":{"1":{"star_index":2111106,"get_star_ts":1733893452},"2":{"star_index":2114508,"get_star_ts":1733893934}},"5":{"1":{"get_star_ts":1733375195,"star_index":1056085},"2":{"get_star_ts":1733375688,"star_index":1059188}},"9":{"2":{"star_index":1802633,"get_star_ts":1733722023},"1":{"get_star_ts":1733721146,"star_index":1799253}},"8":{"2":{"star_index":1635154,"get_star_ts":1733635289},"1":{"star_index":1633492,"get_star_ts":1733635007}},"6":{"2":{"star_index":1276318,"get_star_ts":1733462520},"1":{"star_index":1273266,"get_star_ts":1733462009}}},"id":241985,"last_star_ts":1734153828,"name":"davidsenica","stars":28,"local_score":504,"global_score":26}},"owner_id":427349,"event":"2024"}