{"owner_id":427349,"event":"2022","members":{"229389":{"last_star_ts":1671041092,"global_score":0,"stars":19,"completion_day_level":{"6":{"2":{"get_star_ts":1670343947,"star_index":1517394},"1":{"get_star_ts":1670343922,"star_index":1517291}},"9":{"2":{"get_star_ts":1670763653,"star_index":2472036},"1":{"get_star_ts":1670762340,"star_index":2469090}},"4":{"1":{"get_star_ts":1670146835,"star_index":810353},"2":{"get_star_ts":1670147449,"star_index":813348}},"8":{"2":{"get_star_ts":1670758416,"star_index":2460184},"1":{"get_star_ts":1670696706,"star_index":2355551}},"2":{"1":{"star_index":351345,"get_star_ts":1669997254},"2":{"get_star_ts":1669997736,"star_index":353325}},"7":{"2":{"get_star_ts":1670664701,"star_index":2278922},"1":{"star_index":2276781,"get_star_ts":1670663872}},"10":{"1":{"get_star_ts":1671041092,"star_index":2924019}},"5":{"2":{"star_index":1208115,"get_star_ts":1670260250},"1":{"star_index":1205719,"get_star_ts":1670259630}},"3":{"1":{"star_index":554494,"get_star_ts":1670065044},"2":{"star_index":561715,"get_star_ts":1670066793}},"1":{"1":{"star_index":104014,"get_star_ts":1669930700},"2":{"get_star_ts":1669931517,"star_index":106603}}},"name":"klemen kobau","local_score":103,"id":229389},"2419554":{"last_star_ts":1671028146,"global_score":0,"local_score":204,"id":2419554,"stars":28,"name":"Rok Koleša","completion_day_level":{"11":{"1":{"star_index":2529458,"get_star_ts":1670788785},"2":{"star_index":2561547,"get_star_ts":1670806593}},"5":{"1":{"star_index":1052383,"get_star_ts":1670222149},"2":{"get_star_ts":1670224848,"star_index":1062636}},"3":{"2":{"get_star_ts":1670065695,"star_index":557229},"1":{"star_index":526162,"get_star_ts":1670058242}},"14":{"1":{"get_star_ts":1671027294,"star_index":2903008},"2":{"get_star_ts":1671028146,"star_index":2904358}},"10":{"2":{"get_star_ts":1670674101,"star_index":2303303},"1":{"star_index":2296375,"get_star_ts":1670671298}},"1":{"1":{"star_index":103735,"get_star_ts":1669930615},"2":{"get_star_ts":1669930796,"star_index":104304}},"6":{"1":{"star_index":1374929,"get_star_ts":1670309856},"2":{"get_star_ts":1670310041,"star_index":1375828}},"9":{"2":{"get_star_ts":1670581778,"star_index":2110667},"1":{"get_star_ts":1670567180,"star_index":2073108}},"13":{"2":{"star_index":2803402,"get_star_ts":1670956043},"1":{"get_star_ts":1670946760,"star_index":2788209}},"4":{"2":{"get_star_ts":1670147999,"star_index":816052},"1":{"star_index":815609,"get_star_ts":1670147908}},"12":{"2":{"get_star_ts":1670835999,"star_index":2605036},"1":{"get_star_ts":1670834515,"star_index":2602254}},"8":{"2":{"get_star_ts":1670483075,"star_index":1870581},"1":{"get_star_ts":1670480181,"star_index":1860634}},"7":{"2":{"get_star_ts":1670394479,"star_index":1637936},"1":{"get_star_ts":1670392474,"star_index":1629698}},"2":{"2":{"star_index":192949,"get_star_ts":1669963336},"1":{"star_index":188694,"get_star_ts":1669962361}}}},"2570738":{"global_score":0,"last_star_ts":1671001185,"id":2570738,"local_score":165,"stars":26,"name":"Bogatejc","completion_day_level":{"12":{"1":{"star_index":2589816,"get_star_ts":1670827607},"2":{"get_star_ts":1670827885,"star_index":2590323}},"4":{"1":{"star_index":766961,"get_star_ts":1670135433},"2":{"get_star_ts":1670135440,"star_index":766979}},"9":{"2":{"get_star_ts":1670615918,"star_index":2189318},"1":{"get_star_ts":1670615599,"star_index":2188708}},"6":{"2":{"star_index":1377725,"get_star_ts":1670310436},"1":{"star_index":1377125,"get_star_ts":1670310315}},"13":{"2":{"get_star_ts":1671001185,"star_index":2863767},"1":{"star_index":2818371,"get_star_ts":1670965035}},"2":{"2":{"star_index":635699,"get_star_ts":1670087065},"1":{"star_index":396001,"get_star_ts":1670009946}},"7":{"2":{"star_index":1699629,"get_star_ts":1670415627},"1":{"star_index":1698382,"get_star_ts":1670415153}},"8":{"2":{"get_star_ts":1670526305,"star_index":1993172},"1":{"star_index":1993056,"get_star_ts":1670526260}},"11":{"2":{"star_index":2472983,"get_star_ts":1670764063},"1":{"star_index":2445312,"get_star_ts":1670751744}},"1":{"2":{"get_star_ts":1670087625,"star_index":637576},"1":{"get_star_ts":1670008277,"star_index":390870}},"10":{"2":{"get_star_ts":1670655870,"star_index":2259460},"1":{"star_index":2257923,"get_star_ts":1670655152}},"3":{"1":{"star_index":632902,"get_star_ts":1670086246},"2":{"star_index":632948,"get_star_ts":1670086258}},"5":{"1":{"get_star_ts":1670271676,"star_index":1250931},"2":{"star_index":1252057,"get_star_ts":1670271950}}}},"427349":{"stars":26,"completion_day_level":{"9":{"1":{"star_index":2162497,"get_star_ts":1670603089},"2":{"get_star_ts":1670610089,"star_index":2177604}},"13":{"1":{"star_index":2798317,"get_star_ts":1670952864},"2":{"star_index":2801396,"get_star_ts":1670954791}},"6":{"1":{"get_star_ts":1670310556,"star_index":1378307},"2":{"get_star_ts":1670342868,"star_index":1513758}},"4":{"2":{"get_star_ts":1670145109,"star_index":802378},"1":{"star_index":802156,"get_star_ts":1670145062}},"12":{"1":{"star_index":2602571,"get_star_ts":1670834693},"2":{"get_star_ts":1670835343,"star_index":2603796}},"8":{"1":{"star_index":1989581,"get_star_ts":1670524916},"2":{"get_star_ts":1670527858,"star_index":1996977}},"2":{"2":{"star_index":363646,"get_star_ts":1670000282},"1":{"get_star_ts":1669999285,"star_index":359663}},"7":{"2":{"get_star_ts":1670427280,"star_index":1732154},"1":{"get_star_ts":1670426785,"star_index":1730676}},"11":{"2":{"star_index":2485358,"get_star_ts":1670769466},"1":{"get_star_ts":1670754494,"star_index":2451234}},"5":{"1":{"get_star_ts":1670253335,"star_index":1180199},"2":{"star_index":1180494,"get_star_ts":1670253408}},"3":{"2":{"star_index":545462,"get_star_ts":1670062890},"1":{"get_star_ts":1670061382,"star_index":538942}},"10":{"2":{"star_index":2265103,"get_star_ts":1670658677},"1":{"get_star_ts":1670657593,"star_index":2262911}},"1":{"1":{"get_star_ts":1669908666,"star_index":28737},"2":{"get_star_ts":1669909727,"star_index":32662}}},"name":"Blarc","local_score":174,"id":427349,"global_score":0,"last_star_ts":1670954791},"241985":{"last_star_ts":1670996798,"global_score":0,"id":241985,"local_score":249,"name":"davidsenica","completion_day_level":{"1":{"2":{"star_index":278,"get_star_ts":1669900990},"1":{"get_star_ts":1669900900,"star_index":0}},"10":{"2":{"get_star_ts":1670650918,"star_index":2245062},"1":{"star_index":2235709,"get_star_ts":1670649440}},"14":{"2":{"star_index":2853700,"get_star_ts":1670996798},"1":{"star_index":2852306,"get_star_ts":1670996379}},"5":{"1":{"get_star_ts":1670218117,"star_index":1028298},"2":{"star_index":1030549,"get_star_ts":1670218378}},"3":{"1":{"star_index":501401,"get_star_ts":1670051189},"2":{"get_star_ts":1670051719,"star_index":503137}},"11":{"2":{"get_star_ts":1670739084,"star_index":2421091},"1":{"star_index":2416798,"get_star_ts":1670737790}},"7":{"2":{"star_index":1632921,"get_star_ts":1670393202},"1":{"get_star_ts":1670392751,"star_index":1630983}},"2":{"2":{"get_star_ts":1669962235,"star_index":188099},"1":{"get_star_ts":1669961905,"star_index":186545}},"8":{"1":{"star_index":1840879,"get_star_ts":1670476674},"2":{"star_index":1847005,"get_star_ts":1670477568}},"12":{"2":{"get_star_ts":1670823092,"star_index":2578302},"1":{"star_index":2577948,"get_star_ts":1670822985}},"4":{"1":{"star_index":783320,"get_star_ts":1670140378},"2":{"get_star_ts":1670140845,"star_index":784974}},"9":{"1":{"star_index":2057276,"get_star_ts":1670563430},"2":{"star_index":2059115,"get_star_ts":1670563762}},"6":{"2":{"star_index":1324631,"get_star_ts":1670303213},"1":{"get_star_ts":1670303169,"star_index":1323446}},"13":{"1":{"star_index":2722705,"get_star_ts":1670909114},"2":{"get_star_ts":1670909616,"star_index":2724322}}},"stars":28},"2612006":{"last_star_ts":1670156553,"global_score":0,"stars":8,"completion_day_level":{"3":{"1":{"star_index":839172,"get_star_ts":1670152749},"2":{"star_index":841427,"get_star_ts":1670153250}},"2":{"1":{"star_index":809845,"get_star_ts":1670146735},"2":{"get_star_ts":1670150108,"star_index":826501}},"1":{"2":{"star_index":639237,"get_star_ts":1670088098},"1":{"star_index":636591,"get_star_ts":1670087330}},"4":{"2":{"get_star_ts":1670156553,"star_index":856007},"1":{"get_star_ts":1670154690,"star_index":847826}}},"name":"martinjurkovic","id":2612006,"local_score":24},"1578491":{"completion_day_level":{"3":{"2":{"star_index":1918791,"get_star_ts":1670498836},"1":{"get_star_ts":1670493864,"star_index":1904483}},"2":{"2":{"star_index":1691711,"get_star_ts":1670412552},"1":{"star_index":1685843,"get_star_ts":1670410428}},"1":{"1":{"star_index":1220622,"get_star_ts":1670263678},"2":{"get_star_ts":1670264058,"star_index":1222013}}},"name":"Aljaž Šmaljcelj","stars":6,"id":1578491,"local_score":10,"global_score":0,"last_star_ts":1670498836},"2731000":{"stars":8,"name":"Gal Petkovšek","completion_day_level":{"3":{"1":{"star_index":1720827,"get_star_ts":1670423436},"2":{"star_index":1722061,"get_star_ts":1670423855}},"1":{"2":{"get_star_ts":1670364737,"star_index":1583232},"1":{"star_index":1582192,"get_star_ts":1670364360}},"2":{"2":{"star_index":1705552,"get_star_ts":1670417918},"1":{"star_index":1704214,"get_star_ts":1670417415}},"7":{"2":{"get_star_ts":1670422257,"star_index":1717425},"1":{"star_index":1715433,"get_star_ts":1670421533}}},"local_score":18,"id":2731000,"global_score":0,"last_star_ts":1670423855},"2611525":{"global_score":0,"last_star_ts":1670399699,"stars":12,"completion_day_level":{"4":{"1":{"get_star_ts":1670154611,"star_index":847453},"2":{"star_index":849860,"get_star_ts":1670155144}},"1":{"1":{"star_index":634893,"get_star_ts":1670086840},"2":{"star_index":635661,"get_star_ts":1670087057}},"2":{"1":{"get_star_ts":1670085204,"star_index":629290},"2":{"get_star_ts":1670085837,"star_index":631478}},"7":{"1":{"get_star_ts":1670398654,"star_index":1650958},"2":{"star_index":1653949,"get_star_ts":1670399699}},"5":{"1":{"get_star_ts":1670270702,"star_index":1247105},"2":{"get_star_ts":1670271255,"star_index":1249229}},"3":{"1":{"star_index":642344,"get_star_ts":1670089030},"2":{"get_star_ts":1670089657,"star_index":644397}}},"name":"yanskee","id":2611525,"local_score":58}}}